pyliteral/__init__.py
pyliteral/consts.py
pyliteral/load.py
pyliteral/loads.py
pyliteral/types.py
pyliteral-0.2.0.dist-info/LICENSE
pyliteral-0.2.0.dist-info/METADATA
pyliteral-0.2.0.dist-info/WHEEL
pyliteral-0.2.0.dist-info/top_level.txt
pyliteral-0.2.0.dist-info/RECORD
