Metadata-Version: 2.1
Name: pyliteral
Version: 0.2.0
Summary: A truly Pythonic config format - Designed for both humans and machines.
Author-email: Sreenath Somarajapuram <somarajapuram@gmail.com>
License: Apache License
Project-URL: Homepage, https://github.com/sreenaths/pyliteral
Project-URL: Repository, https://github.com/sreenaths/pyliteral
Classifier: License :: OSI Approved :: Apache Software License
Requires-Python: >=3.8
License-File: LICENSE
